TayloredTiles/T3.py
TayloredTiles/__init__.py
TayloredTiles-1.0.1.dist-info/LICENSE
TayloredTiles-1.0.1.dist-info/METADATA
TayloredTiles-1.0.1.dist-info/WHEEL
TayloredTiles-1.0.1.dist-info/top_level.txt
TayloredTiles-1.0.1.dist-info/RECORD
