Metadata-Version: 2.1
Name: TayloredTiles
Version: 1.0.1
Summary: UNKNOWN
Home-page: UNKNOWN
Author: PyRiscV
Author-email: pyriscv@gmail.com
License: MIT
Platform: UNKNOWN
Classifier: License :: OSI Approved :: MIT License
Classifier: Programming Language :: Python
Classifier: Programming Language :: Python :: 3
License-File: LICENSE
Requires-Dist: numpy
Requires-Dist: sympy
